Workbook

Sheet Dealer Profile
A1: Desert Ridge Auto Group — Dealer Profile & Strategy
A2: Single decision-maker persona: Mike Reynolds, Used-Car Manager (sources inventory & tracks lot performance)
A4: Attribute | B4: Value | E4: Model / Economic Constants
A5: Dealership | B5: Desert Ridge Auto Group | E5: Holding cost / day ($) | F5: 18
A6: Location | B6: Phoenix, Arizona | E6: Target GP / unit ($) | F6: 4000
A7: Type | B7: Independent used-car dealership | E7: Auction fees ($) | F7: 500
A8: Current inventory | B8: 125 vehicles | E8: Marketing ($) | F8: 100
A9: Monthly acquisitions | B9: 60 vehicles | E9: Min P(sale ≤45d) | F9: 0.75
A10: Monthly sales | B10: 55–65 vehicles | E10: Max P(loss) | F10: 0.08
A11: Target days-to-sale | B11: 45 days
A12: Current avg days-to-sale | B12: 72 days | E12: Blue = input · referenced by the Candidate Vehicles tab
A13: Target gross profit / unit | B13: $4,000+
A14: Current avg gross profit / unit | B14: $3,600 | E14: Risk thresholds (Moderate)
A15: Capital available for inventory | B15: $2,000,000 | E15: P(sale ≤45 days) | F15: ≥ 75%
A16: Risk appetite | B16: Moderate | E16: P(sale after 90 days) | F16: ≤ 10%
A17: Primary objective | B17: Balanced velocity + profitability | E17: P(loss) | F17: ≤ 8%
E18: Max mileage | F18: 100,000 mi
E19: Recon uncertainty | F19: Moderate

Sheet Segment Mix
A1: Target Inventory Mix & Portfolio Gaps
A3: Segment | B3: Target % | C3: Current % | D3: Gap (pts) | E3: Interpretation
A4: Compact SUV | B4: 0.25 | C4: 0.18 | D4: =(C4-B4) -> -0.07 | E4: Significant shortage
A5: Midsize SUV | B5: 0.2 | C5: 0.24 | D5: =(C5-B5) -> 0.04 | E5: Slightly overrepresented
A6: Pickup Truck | B6: 0.2 | C6: 0.17 | D6: =(C6-B6) -> -0.03 | E6: Moderate shortage
A7: Sedan | B7: 0.15 | C7: 0.22 | D7: =(C7-B7) -> 0.07 | E7: Overrepresented
A8: Luxury | B8: 0.1 | C8: 0.07 | D8: =(C8-B8) -> -0.03 | E8: Slight shortage
A9: Minivan | B9: 0.05 | C9: 0.04 | D9: =(C9-B9) -> -0.01 | E9: Neutral
A10: Other | B10: 0.05 | C10: 0.08 | D10: =(C10-B10) -> 0.03 | E10: Slightly overrepresented
A13: Gap = Current − Target. Negative = shortage (positive portfolio fit for that segment); positive = overrepresented (negative fit).

Sheet Candidate Vehicles
A1: 20 Candidate Vehicles — Desert Ridge Auto Group (Phoenix)
A2: Predictions (blue) are model outputs; economics (black) are formulas. Holding = days × $18; Non-purchase = recon+fees+transport+marketing+holding; Contribution = sale price − bid − non-purchase; Max buy = sale price − non-purchase − $4,000 target GP.
A3: S.no | B3: Archetype | C3: Year | D3: Make | E3: Model | F3: Trim | G3: Segment | H3: Mileage | I3: Title | J3: Accident | K3: Cond (1-5) | L3: Auction | M3: Dist (mi) | N3: Current Bid | O3: Recon Est | P3: Fees | Q3: Transport | R3: Marketing | S3: Exp Days | T3: Holding | U3: Non-Purch Cost | V3: Exp Sale (P50) | W3: P10 | X3: P90 | Y3: Exp Contribution | Z3: Rec. Max Buy | AA3: Headroom | AB3: Confidence | AC3: P(≤45d) | AD3: P(loss) | AE3: Portfolio Fit | AF3: Recommendation | AG3: Primary Reason
A4: 1 | B4: Strong demand + economics | C4: 2022 | D4: Honda | E4: CR-V | F4: EX-L | G4: Compact SUV | H4: 32400 | I4: Clean | J4: None | K4: 4.2 | L4: Manheim Phoenix | M4: 15 | N4: 22500 | O4: 900 | P4: 500 | Q4: 400 | R4: 100 | S4: 38 | T4: =S4*'Dealer Profile'!$F$5 -> 684 | U4: =O4+P4+Q4+R4+T4 -> 2584 | V4: 29800 | W4: 28900 | X4: 30700 | Y4: =V4-N4-U4 -> 4716 | Z4: =V4-U4-'Dealer Profile'!$F$6 -> 23216 | AA4: =Z4-N4 -> 716 | AB4: High | AC4: 0.84 | AD4: 0.03 | AE4: Positive — compact-SUV shortage | AF4: BUY | AG4: Strong local demand, priced below market, segment shortage.
A5: 2 | B5: Strong demand + economics | C5: 2021 | D5: Toyota | E5: RAV4 | F5: XLE | G5: Compact SUV | H5: 41000 | I5: Clean | J5: None | K5: 4.3 | L5: ADESA Phoenix | M5: 20 | N5: 23000 | O5: 850 | P5: 500 | Q5: 400 | R5: 100 | S5: 34 | T5: =S5*'Dealer Profile'!$F$5 -> 612 | U5: =O5+P5+Q5+R5+T5 -> 2462 | V5: 30500 | W5: 29600 | X5: 31400 | Y5: =V5-N5-U5 -> 5038 | Z5: =V5-U5-'Dealer Profile'!$F$6 -> 24038 | AA5: =Z5-N5 -> 1038 | AB5: High | AC5: 0.89 | AD5: 0.03 | AE5: Positive — compact-SUV shortage | AF5: BUY | AG5: Fastest turn in set; strong demand + shortage.
A6: 3 | B6: Strong truck demand | C6: 2022 | D6: Ford | E6: F-150 | F6: XLT | G6: Pickup Truck | H6: 48000 | I6: Clean | J6: None | K6: 4.1 | L6: Manheim Phoenix | M6: 15 | N6: 28500 | O6: 1800 | P6: 500 | Q6: 400 | R6: 100 | S6: 41 | T6: =S6*'Dealer Profile'!$F$5 -> 738 | U6: =O6+P6+Q6+R6+T6 -> 3538 | V6: 37200 | W6: 36000 | X6: 38400 | Y6: =V6-N6-U6 -> 5162 | Z6: =V6-U6-'Dealer Profile'!$F$6 -> 29662 | AA6: =Z6-N6 -> 1162 | AB6: High | AC6: 0.78 | AD6: 0.04 | AE6: Positive — pickup shortage | AF6: BUY | AG6: Strong truck demand and pickup shortage.
A7: 4 | B7: Good car, overpriced | C7: 2022 | D7: Toyota | E7: Highlander | F7: XLE | G7: Midsize SUV | H7: 38000 | I7: Clean | J7: None | K7: 4.6 | L7: Manheim Phoenix | M7: 15 | N7: 34000 | O7: 1200 | P7: 500 | Q7: 400 | R7: 100 | S7: 35 | T7: =S7*'Dealer Profile'!$F$5 -> 630 | U7: =O7+P7+Q7+R7+T7 -> 2830 | V7: 39500 | W7: 38300 | X7: 40700 | Y7: =V7-N7-U7 -> 2670 | Z7: =V7-U7-'Dealer Profile'!$F$6 -> 32670 | AA7: =Z7-N7 -> -1330 | AB7: High | AC7: 0.86 | AD7: 0.03 | AE7: Slightly negative — midsize over | AF7: NEGOTIATE | AG7: Great car, bid above max buy — negotiate below ~$32.7k.
A8: 5 | B8: High profit, slow turn | C8: 2021 | D8: BMW | E8: 530i | F8: Luxury | G8: Luxury | H8: 42000 | I8: Clean | J8: None | K8: 4.4 | L8: ADESA Phoenix | M8: 20 | N8: 31000 | O8: 1400 | P8: 500 | Q8: 400 | R8: 100 | S8: 76 | T8: =S8*'Dealer Profile'!$F$5 -> 1368 | U8: =O8+P8+Q8+R8+T8 -> 3768 | V8: 41500 | W8: 39800 | X8: 43200 | Y8: =V8-N8-U8 -> 6732 | Z8: =V8-U8-'Dealer Profile'!$F$6 -> 33732 | AA8: =Z8-N8 -> 2732 | AB8: Medium | AC8: 0.42 | AD8: 0.09 | AE8: Segment short but too slow | AF8: PASS | AG8: High gross but 76-day turn fails 45-day velocity target.
A9: 6 | B9: Fast turn, low margin | C9: 2022 | D9: Toyota | E9: Corolla | F9: LE | G9: Sedan | H9: 29000 | I9: Clean | J9: None | K9: 4.3 | L9: Manheim Phoenix | M9: 15 | N9: 17500 | O9: 400 | P9: 500 | Q9: 400 | R9: 100 | S9: 22 | T9: =S9*'Dealer Profile'!$F$5 -> 396 | U9: =O9+P9+Q9+R9+T9 -> 1796 | V9: 21200 | W9: 20600 | X9: 21800 | Y9: =V9-N9-U9 -> 1904 | Z9: =V9-U9-'Dealer Profile'!$F$6 -> 15404 | AA9: =Z9-N9 -> -2096 | AB9: High | AC9: 0.94 | AD9: 0.02 | AE9: Negative — sedan over | AF9: PASS | AG9: Very liquid but expected margin below $4k target.
A10: 7 | B10: Good vehicle, inventory overexposure | C10: 2022 | D10: Toyota | E10: Camry | F10: SE | G10: Sedan | H10: 35000 | I10: Clean | J10: None | K10: 4.4 | L10: Manheim Phoenix | M10: 15 | N10: 21500 | O10: 700 | P10: 500 | Q10: 400 | R10: 100 | S10: 36 | T10: =S10*'Dealer Profile'!$F$5 -> 648 | U10: =O10+P10+Q10+R10+T10 -> 2348 | V10: 28000 | W10: 27200 | X10: 28800 | Y10: =V10-N10-U10 -> 4152 | Z10: =V10-U10-'Dealer Profile'!$F$6 -> 21652 | AA10: =Z10-N10 -> 152 | AB10: High | AC10: 0.86 | AD10: 0.03 | AE10: Strong negative — 14 Camrys vs 8 | AF10: CONDITIONAL | AG10: Attractive alone, but overexposed — buy only below ~$20,500.
A11: 8 | B11: High recon uncertainty | C11: 2021 | D11: Ford | E11: Explorer | F11: XLT | G11: Midsize SUV | H11: 67000 | I11: Clean | J11: None | K11: 3.6 | L11: ADESA Phoenix | M11: 20 | N11: 20000 | O11: 3000 | P11: 500 | Q11: 400 | R11: 100 | S11: 44 | T11: =S11*'Dealer Profile'!$F$5 -> 792 | U11: =O11+P11+Q11+R11+T11 -> 4792 | V11: 28500 | W11: 26500 | X11: 30000 | Y11: =V11-N11-U11 -> 3708 | Z11: =V11-U11-'Dealer Profile'!$F$6 -> 19708 | AA11: =Z11-N11 -> -292 | AB11: Medium | AC11: 0.62 | AD11: 0.22 | AE11: Neutral | AF11: PASS | AG11: Recon $1k–$5k (susp. transmission); downside too uncertain.
A12: 9 | B12: Seasonal opportunity | C12: 2021 | D12: Jeep | E12: Wrangler | F12: Sport | G12: Midsize SUV | H12: 39000 | I12: Clean | J12: None | K12: 4.2 | L12: Manheim Phoenix | M12: 15 | N12: 25500 | O12: 900 | P12: 500 | Q12: 400 | R12: 100 | S12: 39 | T12: =S12*'Dealer Profile'!$F$5 -> 702 | U12: =O12+P12+Q12+R12+T12 -> 2602 | V12: 32000 | W12: 31000 | X12: 33200 | Y12: =V12-N12-U12 -> 3898 | Z12: =V12-U12-'Dealer Profile'!$F$6 -> 25398 | AA12: =Z12-N12 -> -102 | AB12: High | AC12: 0.82 | AD12: 0.04 | AE12: Seasonal uplift 1.25× | AF12: BUY | AG12: Seasonal demand rising; forward-looking turn ≈39 days.
A13: 10 | B13: Nationally strong, locally weak | C13: 2023 | D13: Hyundai | E13: Elantra | F13: SEL | G13: Sedan | H13: 21000 | I13: Clean | J13: None | K13: 4.5 | L13: ADESA Phoenix | M13: 20 | N13: 18500 | O13: 500 | P13: 500 | Q13: 400 | R13: 100 | S13: 67 | T13: =S13*'Dealer Profile'!$F$5 -> 1206 | U13: =O13+P13+Q13+R13+T13 -> 2706 | V13: 23000 | W13: 22200 | X13: 23600 | Y13: =V13-N13-U13 -> 1794 | Z13: =V13-U13-'Dealer Profile'!$F$6 -> 16294 | AA13: =Z13-N13 -> -2206 | AB13: Medium | AC13: 0.48 | AD13: 0.07 | AE13: Negative — local oversupply | AF13: PASS | AG13: Locally weak & high supply — 67-day turn despite national demand.
A14: 11 | B14: Strong dealer segment fit | C14: 2021 | D14: Lexus | E14: RX 350 | F14: Base | G14: Luxury | H14: 45000 | I14: Clean | J14: None | K14: 4.5 | L14: Manheim Phoenix | M14: 15 | N14: 32000 | O14: 900 | P14: 500 | Q14: 400 | R14: 100 | S14: 48 | T14: =S14*'Dealer Profile'!$F$5 -> 864 | U14: =O14+P14+Q14+R14+T14 -> 2764 | V14: 40000 | W14: 38800 | X14: 41400 | Y14: =V14-N14-U14 -> 5236 | Z14: =V14-U14-'Dealer Profile'!$F$6 -> 33236 | AA14: =Z14-N14 -> 1236 | AB14: High | AC14: 0.68 | AD14: 0.05 | AE14: Very strong — 4 luxury vs 12 | AF14: BUY | AG14: Slightly slow generically, but strong luxury shortage → buy.
A15: 12 | B15: High mileage, attractive economics | C15: 2019 | D15: Honda | E15: Accord | F15: Sport | G15: Sedan | H15: 91000 | I15: Clean | J15: None | K15: 3.9 | L15: ADESA Phoenix | M15: 20 | N15: 15000 | O15: 700 | P15: 500 | Q15: 400 | R15: 100 | S15: 43 | T15: =S15*'Dealer Profile'!$F$5 -> 774 | U15: =O15+P15+Q15+R15+T15 -> 2474 | V15: 21000 | W15: 20200 | X15: 21600 | Y15: =V15-N15-U15 -> 3526 | Z15: =V15-U15-'Dealer Profile'!$F$6 -> 14526 | AA15: =Z15-N15 -> -474 | AB15: Medium | AC15: 0.76 | AD15: 0.06 | AE15: Neutral — outside mileage pref | AF15: CONDITIONAL | AG15: Good economics but 91k mi — buy only if inspection clears.
... A23: 20 | B23: Perfect dealer strategy match | C23: 2022 | D23: Mazda | E23: CX-5 | F23: Touring | G23: Compact SUV | H23: 33000 | I23: Clean | J23: None | K23: 4.5 | L23: Manheim Phoenix | M23: 15 | N23: 21000 | O23: 600 | P23: 500 | Q23: 400 | R23: 100 | S23: 33 | T23: =S23*'Dealer Profile'!$F$5 -> 594 | U23: =O23+P23+Q23+R23+T23 -> 2194 | V23: 27500 | W23: 26700 | X23: 28300 | Y23: =V23-N23-U23 -> 4306 | Z23: =V23-U23-'Dealer Profile'!$F$6 -> 21306 | AA23: =Z23-N23 -> 306 | AB23: High | AC23: 0.9 | AD23: 0.02 | AE23: Very strong — compact-SUV shortage | AF23: BUY | AG23: Textbook fit: ideal miles/price, segment shortage, fast turn.

Sheet Decision Logic
A1: Decision Logic — Prediction Layer ≠ Decision Layer
A3: Core principle | B3: The shared prediction layer estimates what will happen (sell-through, price, cost, risk). The personalized decision layer applies THIS dealer's goals, risk, inventory and capital to output BUY / NEGOTIATE / PASS + a max buy price. Change the dealer's settings and the decision changes with no model retraining.
A4: Economics | B4: Holding = Exp Days × $18/day. Non-purchase cost = Recon + Fees($500) + Transport + Marketing($100) + Holding. Expected contribution = Exp Sale Price − Current Bid − Non-purchase cost. Recommended max buy = Exp Sale Price − Non-purchase cost − $4,000 target GP.
A5: BUY | B5: P(sale ≤45d) ≥ 75% AND Expected contribution ≥ $4,000 (at or below max buy) AND P(loss) ≤ 8% AND no hard-constraint or portfolio-saturation violation.
A6: NEGOTIATE | B6: Vehicle is strong (velocity + demand pass) BUT current bid is above the recommended max buy. Output the max acceptable price. 'Good car, wrong price.'
A7: PASS | B7: Any of: P(sale ≤45d) below target (slow turn) · expected contribution below target even at a fair price (low margin) · P(loss) above tolerance (high uncertainty) · hard-constraint fail (salvage/flood/frame/odometer/severe accident, or mileage > 100k).
A8: CONDITIONAL | B8: Attractive but gated on a condition: a lower price (portfolio overexposure), an inspection (high mileage / recon), or an operational capability (in-house recon). Shown as 'Buy only if / below $X'.
A9: RISK-DEPENDENT | B9: Expected value attractive but wide downside and thin data. Decision flips with the dealer's risk setting — PASS for moderate, BUY for aggressive.
A10: Portfolio adjustment | B10: Vehicle-level attractiveness is adjusted by segment gap (Segment Mix tab) and same-model exposure. A strong car in an oversupplied segment (e.g., 14 Camrys vs target 8) is downgraded to CONDITIONAL/PASS; a good car in a short segment (luxury 4 vs 12) is upgraded.
A11: Hero output | B11: Never a naked score. Always: ACTION + recommended max buy price + P(sale ≤45d) + expected contribution + why. 'Buy this vehicle, but do not exceed $X.'

Sheet Historical Sample
A1: Sample Historical Outcomes — feedback loop for calibration
A2: Each purchased vehicle records predicted vs actual, so the engine is scored on realized outcomes (money made), not model fit alone.
A4: Vehicle | B4: Acquired | C4: Sale Price (pred) | D4: Sale Price (actual) | E4: Days (pred) | F4: Days (actual) | G4: Recon (pred) | H4: Recon (actual) | I4: Contribution (actual) | J4: Sold ≤45d?
A5: 2022 Honda CR-V EX-L | B5: $22,500 | C5: 29800 | D5: 29500 | E5: 38 | F5: 34 | G5: 900 | H5: 1050 | I5: 4650 | J5: Yes
A6: 2021 Toyota RAV4 XLE | B6: $23,000 | C6: 30500 | D6: 30200 | E6: 34 | F6: 31 | G6: 850 | H6: 800 | I6: 5150 | J6: Yes
A7: 2022 Ford F-150 XLT | B7: $28,700 | C7: 37200 | D7: 37500 | E7: 41 | F7: 44 | G7: 1800 | H7: 1650 | I7: 4900 | J7: No
A8: 2021 BMW 530i | B8: $29,500 | C8: 41500 | D8: 40100 | E8: 76 | F8: 71 | G8: 1400 | H8: 1900 | I8: 4200 | J8: No
A9: 2022 Toyota Camry SE | B9: $20,400 | C9: 28000 | D9: 27800 | E9: 36 | F9: 33 | G9: 700 | H9: 720 | I9: 4380 | J9: Yes
A10: 2021 Jeep Wrangler Sport | B10: $25,300 | C10: 32000 | D10: 32600 | E10: 39 | F10: 29 | G10: 900 | H10: 850 | I10: 5100 | J10: Yes
A11: 2021 Lexus RX 350 | B11: $31,600 | C11: 40000 | D11: 39600 | E11: 48 | F11: 52 | G11: 900 | H11: 1150 | I11: 4550 | J11: No
A12: 2022 Mazda CX-5 Touring | B12: $20,800 | C12: 27500 | D12: 27400 | E12: 33 | F12: 30 | G12: 600 | H12: 640 | I12: 4520 | J12: Yes
